model
monitoring_custom_metrics
