Metadata-Version: 2.1
Name: MonitoringCustomMetrics
Version: 1.0.4
Summary: Custom Metrics for ML Model Monitoring
Home-page: https://github.com/amzn/MonitoringCustomMetrics
License: Apache License 2.0
Keywords: MonitoringCustomMetrics ML Monitoring Metrics
Classifier: Development Status :: 4 - Beta
Classifier: Topic :: Utilities
Classifier: License :: OSI Approved
License-File: LICENSE.txt
License-File: NOTICE
